Workbook

Sheet Income Statement
B2: Income Statement
B3: $ in actual figures | C3: 44562 | D3: =EOMONTH(C3,12) -> 44957 | E3: =EOMONTH(D3,12) -> 45322 | F3: =EOMONTH(E3,12) -> 45688 | G3: =EOMONTH(F3,12) -> 46053
B4: Revenue
B5: Gross Revenue | C5: =C32*C33 -> 25000 | D5: =D32*D33 -> 27500 | E5: =E32*E33 -> 32500 | F5: =F32*F33 -> 40000 | G5: =G32*G33 -> 50000
B6: Discounts | C6: =C5*-C34 -> -1250 | D6: =D5*-D34 -> -1375 | E6: =E5*-E34 -> -1625 | F6: =F5*-F34 -> -2000 | G6: =G5*-G34 -> -2500
B7: Net Revenue | C7: =SUM(C5:C6) -> 23750 | D7: =SUM(D5:D6) -> 26125 | E7: =SUM(E5:E6) -> 30875 | F7: =SUM(F5:F6) -> 38000 | G7: =SUM(G5:G6) -> 47500
B8: Cost Of Goods Sold (COGS)
B9: Raw Materials | C9: =C$5*-C37 -> -7500 | D9: =D$5*-D37 -> -8250 | E9: =E$5*-E37 -> -9750 | F9: =F$5*-F37 -> -12000 | G9: =G$5*-G37 -> -15000
B10: Fulfillment | C10: =C$5*-C38 -> -1750 | D10: =D$5*-D38 -> -1925 | E10: =E$5*-E38 -> -2275 | F10: =F$5*-F38 -> -2800 | G10: =G$5*-G38 -> -3500
B11: Transaction Fees | C11: =C$5*-C39 -> -500 | D11: =D$5*-D39 -> -550 | E11: =E$5*-E39 -> -650 | F11: =F$5*-F39 -> -800 | G11: =G$5*-G39 -> -1000
B12: Total COGS | C12: =SUM(C9:C11) -> -9750 | D12: =SUM(D9:D11) -> -10725 | E12: =SUM(E9:E11) -> -12675 | F12: =SUM(F9:F11) -> -15600 | G12: =SUM(G9:G11) -> -19500
B13: Gross Profit | C13: =C7+C12 -> 14000 | D13: =D7+D12 -> 15400 | E13: =E7+E12 -> 18200 | F13: =F7+F12 -> 22400 | G13: =G7+G12 -> 28000
B14: Gross Profit Margin % | C14: =C13/C7 -> 0.58947368 | D14: =D13/D7 -> 0.58947368 | E14: =E13/E7 -> 0.58947368 | F14: =F13/F7 -> 0.58947368 | G14: =G13/G7 -> 0.58947368
B15: Operating Expenses
B16: Labor | C16: =C$5*-C42 -> -3750 | D16: =D$5*-D42 -> -4125 | E16: =E$5*-E42 -> -4875 | F16: =F$5*-F42 -> -6000 | G16: =G$5*-G42 -> -7500
B17: Marketing | C17: =C$5*-C43 -> -1250 | D17: =D$5*-D43 -> -1375 | E17: =E$5*-E43 -> -1625 | F17: =F$5*-F43 -> -2000 | G17: =G$5*-G43 -> -2500
B18: SGA & Other | C18: =C$5*-C44 -> -1250 | D18: =D$5*-D44 -> -1375 | E18: =E$5*-E44 -> -1625 | F18: =F$5*-F44 -> -2000 | G18: =G$5*-G44 -> -2500
B19: Total OpEx | C19: =SUM(C16:C18) -> -6250 | D19: =SUM(D16:D18) -> -6875 | E19: =SUM(E16:E18) -> -8125 | F19: =SUM(F16:F18) -> -10000 | G19: =SUM(G16:G18) -> -12500
B20: EBITDA | C20: =C13+C19 -> 7750 | D20: =D13+D19 -> 8525 | E20: =E13+E19 -> 10075 | F20: =F13+F19 -> 12400 | G20: =G13+G19 -> 15500
B21: Depreciation & Amortization | C21: =-'Fixed Assets'!D15 -> -4952.381 | D21: =-'Fixed Assets'!E15 -> -4952.381 | E21: =-'Fixed Assets'!F15 -> -4952.381 | F21: =-'Fixed Assets'!G15 -> -4952.381 | G21: =-'Fixed Assets'!H15 -> -2952.381
B22: EBIT | C22: =SUM(C20:C21) -> 2797.619 | D22: =SUM(D20:D21) -> 3572.619 | E22: =SUM(E20:E21) -> 5122.619 | F22: =SUM(F20:F21) -> 7447.619 | G22: =SUM(G20:G21) -> 12547.619
B23: Interest & Expense | C23: =-'Balance Sheet'!D42 -> -665 | D23: =-'Balance Sheet'!E42 -> -630 | E23: =-'Balance Sheet'!F42 -> -927.5 | F23: =-'Balance Sheet'!G42 -> -875 | G23: =-'Balance Sheet'!H42 -> -822.5
B24: EBT | C24: =SUM(C22:C23) -> 2132.619 | D24: =SUM(D22:D23) -> 2942.619 | E24: =SUM(E22:E23) -> 4195.119 | F24: =SUM(F22:F23) -> 6572.619 | G24: =SUM(G22:G23) -> 11725.119
B25: Taxes | C25: =-C24*C46 -> -447.85 | D25: =-D24*D46 -> -617.95 | E25: =-E24*E46 -> -880.975 | F25: =-F24*F46 -> -1380.25 | G25: =-G24*G46 -> -2462.275
B26: Net Income | C26: =SUM(C24:C25) -> 1684.769 | D26: =SUM(D24:D25) -> 2324.669 | E26: =SUM(E24:E25) -> 3314.144 | F26: =SUM(F24:F25) -> 5192.369 | G26: =SUM(G24:G25) -> 9262.844
B28: Net Income as % of Revenue | C28: =C26/C7 -> 0.070937644 | D28: =D26/D7 -> 0.088982547 | E28: =E26/E7 -> 0.1073407 | F28: =F26/F7 -> 0.13664129 | G28: =G26/G7 -> 0.19500724
B30: Assumptions:
B31: Revenue
B32: Cups Sold | C32: 5000 | D32: 5500 | E32: 6500 | F32: 8000 | G32: 10000
B33: Average Price per Cup | C33: 5 | D33: 5 | E33: 5 | F33: 5 | G33: 5
B34: =B6&" as a % of Revenue " -> Discounts as a % of Revenue | C34: 0.05 | D34: 0.05 | E34: 0.05 | F34: 0.05 | G34: 0.05
B36: Cost of Goods Sold (COGS)
B37: =B9&" as a % of Revenue " -> Raw Materials as a % of Revenue | C37: 0.3 | D37: 0.3 | E37: 0.3 | F37: 0.3 | G37: 0.3
B38: =B10&" as a % of Revenue " -> Fulfillment as a % of Revenue | C38: 0.07 | D38: 0.07 | E38: 0.07 | F38: 0.07 | G38: 0.07
B39: =B11&" as a % of Revenue " -> Transaction Fees as a % of Revenue | C39: 0.02 | D39: 0.02 | E39: 0.02 | F39: 0.02 | G39: 0.02
B41: Operating Expenses
B42: Labor as a % of revenue | C42: 0.15 | D42: 0.15 | E42: 0.15 | F42: 0.15 | G42: 0.15
B43: Marketing as a % of revenue | C43: 0.05 | D43: 0.05 | E43: 0.05 | F43: 0.05 | G43: 0.05
B44: SG&A as a % of revenue | C44: 0.05 | D44: 0.05 | E44: 0.05 | F44: 0.05 | G44: 0.05
B46: Corporate Tax Rate | C46: 0.21 | D46: 0.21 | E46: 0.21 | F46: 0.21 | G46: 0.21

Sheet Balance Sheet
B2: Balance Sheet | C2: Historical
B3: $ in actual figures | C3: 44561 | D3: =EDATE(C3,12) -> 44926 | E3: =EDATE(D3,12) -> 45291 | F3: =EDATE(E3,12) -> 45657 | G3: =EDATE(F3,12) -> 46022 | H3: =EDATE(G3,12) -> 46387
B4: Current Assets
B5: Cash | C5: 5000 | D5: =C5+'Cash Flow Statement'!C18 -> -2871.6777 | E5: =D5+'Cash Flow Statement'!D18 -> 3919.4895 | F5: =E5+'Cash Flow Statement'!E18 -> 16464.249 | G5: =F5+'Cash Flow Statement'!F18 -> 20901.351 | H5: =G5+'Cash Flow Statement'!G18 -> 32423.045
B6: Accounts Receivable | C6: 150 | D6: =D34*D32 -> 237.5 | E6: =E34*E32 -> 261.25 | F6: =F34*F32 -> 308.75 | G6: =G34*G32 -> 380 | H6: =H34*H32 -> 475
B7: Total Current Assets | C7: =SUM(C5:C6) -> 5150 | D7: =SUM(D5:D6) -> -2634.1777 | E7: =SUM(E5:E6) -> 4180.7395 | F7: =SUM(F5:F6) -> 16772.999 | G7: =SUM(G5:G6) -> 21281.351 | H7: =SUM(H5:H6) -> 32898.045
B8: Non Current Assets
B9: Fixed Assets | C9: 10000 | D9: =C9+'Fixed Assets'!D8 -> 24000 | E9: =D9+'Fixed Assets'!E8 -> 24000 | F9: =E9+'Fixed Assets'!F8 -> 24000 | G9: =F9+'Fixed Assets'!G8 -> 29000 | H9: =G9+'Fixed Assets'!H8 -> 29000
B10: Accumulated Depreciation | C10: -2000 | D10: =C10-'Fixed Assets'!D15 -> -6952.381 | E10: =D10-'Fixed Assets'!E15 -> -11904.762 | F10: =E10-'Fixed Assets'!F15 -> -16857.143 | G10: =F10-'Fixed Assets'!G15 -> -21809.524 | H10: =G10-'Fixed Assets'!H15 -> -24761.905
B11: Net Fixed Assets | C11: =SUM(C9:C10) -> 8000 | D11: =SUM(D9:D10) -> 17047.619 | E11: =SUM(E9:E10) -> 12095.238 | F11: =SUM(F9:F10) -> 7142.8571 | G11: =SUM(G9:G10) -> 7190.4762 | H11: =SUM(H9:H10) -> 4238.0952
B12: Total Non Current Assets | C12: =C11 -> 8000 | D12: =D11 -> 17047.619 | E12: =E11 -> 12095.238 | F12: =F11 -> 7142.8571 | G12: =G11 -> 7190.4762 | H12: =H11 -> 4238.0952
B13: Total Assets | C13: =C12+C7 -> 13150 | D13: =D12+D7 -> 14413.441 | E13: =E12+E7 -> 16275.978 | F13: =F12+F7 -> 23915.856 | G13: =G12+G7 -> 28471.827 | H13: =H12+H7 -> 37136.14
B15: Current Liabilities
B16: Accounts Payable | C16: 200 | D16: =D35*D33 -> 220.33898 | E16: =E35*E33 -> 242.37288 | F16: =F35*F33 -> 286.44068 | G16: =G35*G33 -> 352.54237 | H16: =H35*H33 -> 440.67797
B17: Deferred Revenue | C17: 100 | D17: =D36*D32 -> 158.33333 | E17: =E36*E32 -> 174.16667 | F17: =F36*F32 -> 205.83333 | G17: =G36*G32 -> 253.33333 | H17: =H36*H32 -> 316.66667
B18: Total Current Liabilitites | C18: =SUM(C16:C17) -> 300 | D18: =SUM(D16:D17) -> 378.67232 | E18: =SUM(E16:E17) -> 416.53955 | F18: =SUM(F16:F17) -> 492.27401 | G18: =SUM(G16:G17) -> 605.87571 | H18: =SUM(H16:H17) -> 757.34463
B19: Non Current Liabilities
B20: Debt | C20: 10000 | D20: =C20+D39-D40 -> 9500 | E20: =D20+E39-E40 -> 9000 | F20: =E20+F39-F40 -> 13250 | G20: =F20+G39-G40 -> 12500 | H20: =G20+H39-H40 -> 11750
B21: Total Non Current Liabilitites | C21: =C20 -> 10000 | D21: =D20 -> 9500 | E21: =E20 -> 9000 | F21: =F20 -> 13250 | G21: =G20 -> 12500 | H21: =H20 -> 11750
B22: Total Liabilitites | C22: =C18+C21 -> 10300 | D22: =D18+D21 -> 9878.6723 | E22: =E18+E21 -> 9416.5395 | F22: =F18+F21 -> 13742.274 | G22: =G18+G21 -> 13105.876 | H22: =H18+H21 -> 12507.345
B23: Equity
B24: Common Stock | C24: 300 | D24: =C24 -> 300 | E24: =D24 -> 300 | F24: =E24 -> 300 | G24: =F24 -> 300 | H24: =G24 -> 300
B25: Retained Earnings | C25: 2550 | D25: =C25+'Income Statement'!C26 -> 4234.769 | E25: =D25+'Income Statement'!D26 -> 6559.4381 | F25: =E25+'Income Statement'!E26 -> 9873.5821 | G25: =F25+'Income Statement'!F26 -> 15065.951 | H25: =G25+'Income Statement'!G26 -> 24328.795
B26: Total Equity | C26: =SUM(C24:C25) -> 2850 | D26: =SUM(D24:D25) -> 4534.769 | E26: =SUM(E24:E25) -> 6859.4381 | F26: =SUM(F24:F25) -> 10173.582 | G26: =SUM(G24:G25) -> 15365.951 | H26: =SUM(H24:H25) -> 24628.795
B27: Total Liabilities & Equity | C27: =C22+C26 -> 13150 | D27: =D22+D26 -> 14413.441 | E27: =E22+E26 -> 16275.978 | F27: =F22+F26 -> 23915.856 | G27: =G22+G26 -> 28471.827 | H27: =H22+H26 -> 37136.14
B29: Balance Check | C29: =C13-C27 -> 0 | D29: =D13-D27 -> 0 | E29: =E13-E27 -> 0 | F29: =F13-F27 -> 0 | G29: =G13-G27 -> 0 | H29: =H13-H27 -> 0
B31: Assumptions:
B32: Net Revenue | C32: 15000 | D32: ='Income Statement'!C7 -> 23750 | E32: ='Income Statement'!D7 -> 26125 | F32: ='Income Statement'!E7 -> 30875 | G32: ='Income Statement'!F7 -> 38000 | H32: ='Income Statement'!G7 -> 47500
B33: COGS | C33: 8850 | D33: =-'Income Statement'!C12 -> 9750 | E33: =-'Income Statement'!D12 -> 10725 | F33: =-'Income Statement'!E12 -> 12675 | G33: =-'Income Statement'!F12 -> 15600 | H33: =-'Income Statement'!G12 -> 19500
B34: =B6&" as a % of Rev" -> Accounts Receivable as a % of Rev | C34: =C6/C32 -> 0.01 | D34: =C34 -> 0.01 | E34: =D34 -> 0.01 | F34: =E34 -> 0.01 | G34: =F34 -> 0.01 | H34: =G34 -> 0.01
B35: =B16& "as a % of COGS" -> Accounts Payableas a % of COGS | C35: =C16/C33 -> 0.02259887 | D35: =C35 -> 0.02259887 | E35: =D35 -> 0.02259887 | F35: =E35 -> 0.02259887 | G35: =F35 -> 0.02259887 | H35: =G35 -> 0.02259887
B36: =B17&" as a % of Rev" -> Deferred Revenue as a % of Rev | C36: =C17/C32 -> 0.0066666667 | D36: =C36 -> 0.0066666667 | E36: =D36 -> 0.0066666667 | F36: =E36 -> 0.0066666667 | G36: =F36 -> 0.0066666667 | H36: =G36 -> 0.0066666667
B38: Debt
B39: Net Borrowing | F39: 5000
B40: Debt Repayment | D40: 500 | E40: 500 | F40: 750 | G40: 750 | H40: 750
B41: Interest Rate | D41: 0.07 | E41: 0.07 | F41: 0.07 | G41: 0.07 | H41: 0.07
B42: Interest Payment | D42: =D41*D20 -> 665 | E42: =E41*E20 -> 630 | F42: =F41*F20 -> 927.5 | G42: =G41*G20 -> 875 | H42: =H41*H20 -> 822.5

Sheet Cash Flow Statement
B2: Statement of Cashflows
B3: $ in actual figures | C3: 44562 | D3: =EDATE(C3,12) -> 44927 | E3: =EDATE(D3,12) -> 45292 | F3: =EDATE(E3,12) -> 45658 | G3: =EDATE(F3,12) -> 46023
B4: Net Income | C4: ='Income Statement'!C26 -> 1684.769 | D4: ='Income Statement'!D26 -> 2324.669 | E4: ='Income Statement'!E26 -> 3314.144 | F4: ='Income Statement'!F26 -> 5192.369 | G4: ='Income Statement'!G26 -> 9262.844
B5: Operating Activities
B6: Depreciation | C6: ='Fixed Assets'!D15 -> 4952.381 | D6: ='Fixed Assets'!E15 -> 4952.381 | E6: ='Fixed Assets'!F15 -> 4952.381 | F6: ='Fixed Assets'!G15 -> 4952.381 | G6: ='Fixed Assets'!H15 -> 2952.381
B7: ="Change in "&'[1]Balance Sheet'!B6 -> Change in Accounts Receivable | C7: =-('Balance Sheet'!D6-'Balance Sheet'!C6) -> -87.5 | D7: =-('Balance Sheet'!E6-'Balance Sheet'!D6) -> -23.75 | E7: =-('Balance Sheet'!F6-'Balance Sheet'!E6) -> -47.5 | F7: =-('Balance Sheet'!G6-'Balance Sheet'!F6) -> -71.25 | G7: =-('Balance Sheet'!H6-'Balance Sheet'!G6) -> -95
B8: ="Change in "&'[1]Balance Sheet'!B16 -> Change in Accounts Payable | C8: =('Balance Sheet'!D16-'Balance Sheet'!C16) -> 20.338983 | D8: =('Balance Sheet'!E16-'Balance Sheet'!D16) -> 22.033898 | E8: =('Balance Sheet'!F16-'Balance Sheet'!E16) -> 44.067797 | F8: =('Balance Sheet'!G16-'Balance Sheet'!F16) -> 66.101695 | G8: =('Balance Sheet'!H16-'Balance Sheet'!G16) -> 88.135593
B9: ="Change in "&'[1]Balance Sheet'!B17 -> Change in Deferred Revenue | C9: =('Balance Sheet'!D17-'Balance Sheet'!C17) -> 58.333333 | D9: =('Balance Sheet'!E17-'Balance Sheet'!D17) -> 15.833333 | E9: =('Balance Sheet'!F17-'Balance Sheet'!E17) -> 31.666667 | F9: =('Balance Sheet'!G17-'Balance Sheet'!F17) -> 47.5 | G9: =('Balance Sheet'!H17-'Balance Sheet'!G17) -> 63.333333
B10: Operating Cash Flow | C10: =SUM(C6:C9) -> 4943.5533 | D10: =SUM(D6:D9) -> 4966.4982 | E10: =SUM(E6:E9) -> 4980.6154 | F10: =SUM(F6:F9) -> 4994.7326 | G10: =SUM(G6:G9) -> 3008.8499
B11: Investing Activities
B12: CapEx | C12: =-('Fixed Assets'!D8) -> -14000 | D12: =-('Fixed Assets'!E8) -> 0 | E12: =-('Fixed Assets'!F8) -> 0 | F12: =-('Fixed Assets'!G8) -> -5000 | G12: =-('Fixed Assets'!H8) -> 0
B13: Investing Cash Flow | C13: =C12 -> -14000 | D13: =D12 -> 0 | E13: =E12 -> 0 | F13: =F12 -> -5000 | G13: =G12 -> 0
B14: Financing Activities
B15: Debt Repayment | C15: =-('Balance Sheet'!D40) -> -500 | D15: =-('Balance Sheet'!E40) -> -500 | E15: =-('Balance Sheet'!F40) -> -750 | F15: =-('Balance Sheet'!G40) -> -750 | G15: =-('Balance Sheet'!H40) -> -750
B16: Net Borrowings | C16: ='Balance Sheet'!D39 -> 0 | D16: ='Balance Sheet'!E39 -> 0 | E16: ='Balance Sheet'!F39 -> 5000 | F16: ='Balance Sheet'!G39 -> 0 | G16: ='Balance Sheet'!H39 -> 0
B17: Financing Cash Flow | C17: =SUM(C15:C16) -> -500 | D17: =SUM(D15:D16) -> -500 | E17: =SUM(E15:E16) -> 4250 | F17: =SUM(F15:F16) -> -750 | G17: =SUM(G15:G16) -> -750
B18: Net Cash Flow | C18: =C4+C10+C13+C17 -> -7871.6777 | D18: =D4+D10+D13+D17 -> 6791.1672 | E18: =E4+E10+E13+E17 -> 12544.759 | F18: =F4+F10+F13+F17 -> 4437.1017 | G18: =G4+G10+G13+G17 -> 11521.694

Sheet Fixed Assets
B2: Fixed Assets
B3: $ in actual figures | C3: Asset Life (Years) | D3: 44926 | E3: =EDATE(D3,12) -> 45291 | F3: =EDATE(E3,12) -> 45657 | G3: =EDATE(F3,12) -> 46022 | H3: =EDATE(G3,12) -> 46387
B4: CapEx
B5: Lemon Crusher | C5: 3 | D5: 5000 | G5: 5000
B6: Ice Machine | C6: 7 | D6: 3000
B7: Refrigerator | C7: 7 | D7: 6000
B8: Total CapEx | D8: =SUM(D5:D7) -> 14000 | E8: =SUM(E5:E7) -> 0 | F8: =SUM(F5:F7) -> 0 | G8: =SUM(G5:G7) -> 5000 | H8: =SUM(H5:H7) -> 0
B10: Depreciation
B11: Existing Equipment | D11: 2000 | E11: 2000 | F11: 2000 | G11: 2000
B12: =B5 -> Lemon Crusher | D12: =$D5/$C5 -> 1666.6667 | E12: =$D5/$C5 -> 1666.6667 | F12: =$D5/$C5 -> 1666.6667 | G12: =$G5/$C5 -> 1666.6667 | H12: =$G5/$C5 -> 1666.6667
B13: =B6 -> Ice Machine | D13: =$D6/$C6 -> 428.57143 | E13: =$D6/$C6 -> 428.57143 | F13: =$D6/$C6 -> 428.57143 | G13: =$D6/$C6 -> 428.57143 | H13: =$D6/$C6 -> 428.57143
B14: =B7 -> Refrigerator | D14: =$D7/$C7 -> 857.14286 | E14: =$D7/$C7 -> 857.14286 | F14: =$D7/$C7 -> 857.14286 | G14: =$D7/$C7 -> 857.14286 | H14: =$D7/$C7 -> 857.14286
B15: Total D&A | D15: =SUM(D11:D14) -> 4952.381 | E15: =SUM(E11:E14) -> 4952.381 | F15: =SUM(F11:F14) -> 4952.381 | G15: =SUM(G11:G14) -> 4952.381 | H15: =SUM(H11:H14) -> 2952.381
